dynfc/__init__.py
dynfc/butter_bandpass_filter.py
dynfc/butter_design.py
dynfc/cc.py
dynfc/cofluct.py
dynfc/corr_slide.py
dynfc/dPL.py
dynfc/doEuclid.py
dynfc/doHilbert.py
dynfc/doKuramoto.py
dynfc/getEntropy.py
dynfc/get_LEiDA.py
dynfc/phDiff.py
dynfc/run_multiPatKOP.py
dynfc/run_multiPatLEiDA.py
tests/__init__.py
tests/test_functions.py
dynfc-0.0.3a1.dist-info/LICENSE
dynfc-0.0.3a1.dist-info/METADATA
dynfc-0.0.3a1.dist-info/WHEEL
dynfc-0.0.3a1.dist-info/top_level.txt
dynfc-0.0.3a1.dist-info/RECORD
