Metadata-Version: 2.1
Name: dynfc
Version: 0.0.3a1
Summary: UNKNOWN
Home-page: https://code-neuro.github.io/dynfc/
Author: Lucas G. S. França, Dafnis Batalle
Author-email: lucas.franca@kcl.ac.uk, dafnis.batalle@kcl.ac.uk
License: UNKNOWN
Platform: UNKNOWN
Classifier: Programming Language :: Python :: 3
Classifier: License :: OSI Approved :: MIT License
Classifier: Operating System :: OS Independent
Requires-Python: >=3.6
License-File: LICENSE
